DataTypeSystem/Examiner.py
DataTypeSystem/Predicates.py
DataTypeSystem/TypeClasses.py
DataTypeSystem/TypeSystem.py
DataTypeSystem/__init__.py
DataTypeSystem-0.1.1.dist-info/LICENSE
DataTypeSystem-0.1.1.dist-info/METADATA
DataTypeSystem-0.1.1.dist-info/WHEEL
DataTypeSystem-0.1.1.dist-info/top_level.txt
DataTypeSystem-0.1.1.dist-info/RECORD
