Metadata-Version: 2.1
Name: DataTypeSystem
Version: 0.1.1
Summary: Data type system for different data structures (arrays, lists of dictionaries, etc.).
Home-page: https://github.com/antononcube/Python-packages/tree/main/DataTypeSystem
Author: Anton Antonov
Author-email: antononcube@posteo.net
Keywords: data structure,type system,types
Classifier: Intended Audience :: Science/Research
Classifier: Intended Audience :: Developers
Classifier: Programming Language :: Python :: 3
Classifier: License :: OSI Approved :: BSD License
Classifier: Intended Audience :: Science/Research
Classifier: Intended Audience :: Developers
Classifier: Operating System :: OS Independent
Requires-Python: >=3.7
License-File: LICENSE
